narxpy/__init__.py
narxpy/model.py
narxpy-0.1.0.dist-info/LICENSE
narxpy-0.1.0.dist-info/METADATA
narxpy-0.1.0.dist-info/WHEEL
narxpy-0.1.0.dist-info/top_level.txt
narxpy-0.1.0.dist-info/RECORD
